anki_mcp/__init__.py
anki_mcp/server.py
anki_mcp/tools/__init__.py
anki_mcp/tools/add_note.py
anki_mcp/tools/check_connection.py
anki_mcp/tools/find_notes.py
anki_mcp/tools/get_cards_reviewed.py
anki_mcp/tools/get_model_fields.py
anki_mcp/tools/list_decks.py
anki_mcp/tools/list_models.py
anki_mcp/tools/update_note.py
anki_mcp/tools/utils.py
anki_mcp-0.1.0.dist-info/METADATA
anki_mcp-0.1.0.dist-info/WHEEL
anki_mcp-0.1.0.dist-info/entry_points.txt
anki_mcp-0.1.0.dist-info/RECORD
