Metadata-Version: 2.4
Name: anki-mcp
Version: 0.1.0
Summary: An Anki MCP server
Author-email: Johannes Wiebe <johanneswiebe@posteo.de>
Requires-Python: >=3.10
Requires-Dist: mcp>=1.5.0
